docnetdb/__init__.py
docnetdb/docnetdb.py
docnetdb/edge.py
docnetdb/exceptions.py
docnetdb/logger.py
docnetdb/vertex.py
docnetdb/examples/__init__.py
docnetdb/examples/edges.py
docnetdb/examples/vertices.py
docnetdb/tests/__init__.py
docnetdb/tests/test_docnetdb.py
docnetdb/tests/test_edge.py
docnetdb/tests/test_vertex.py
docnetdb-0.6.1.dist-info/LICENSE
docnetdb-0.6.1.dist-info/METADATA
docnetdb-0.6.1.dist-info/WHEEL
docnetdb-0.6.1.dist-info/top_level.txt
docnetdb-0.6.1.dist-info/RECORD
