Metadata-Version: 2.1
Name: docnetdb
Version: 0.6.1
Summary: A pure Python document and graph database engine
Home-page: https://github.com/fsabre/DocNetDB
Author: fsabre
Author-email: fabien.sabre@gmail.com
License: MIT
Keywords: document,graph,database,nosql,pure python
Platform: UNKNOWN
Classifier: Development Status :: 4 - Beta
Classifier: Intended Audience :: Developers
Classifier: Topic :: Software Development :: Build Tools
Classifier: License :: OSI Approved :: MIT License
Classifier: Operating System :: OS Independent
Classifier: Programming Language :: Python :: 3
Requires-Python: >=3.6
